transfersh_client/__init__.py
transfersh_client/app.py
transfersh_client-1.1.3.dist-info/LICENSE
transfersh_client-1.1.3.dist-info/METADATA
transfersh_client-1.1.3.dist-info/WHEEL
transfersh_client-1.1.3.dist-info/entry_points.txt
transfersh_client-1.1.3.dist-info/top_level.txt
transfersh_client-1.1.3.dist-info/RECORD
