Metadata-Version: 2.1
Name: transfersh-client
Version: 1.1.3
Summary: transfer.sh command-line client
Home-page: https://github.com/arsenlosenko/transfer.sh_client.git
Author: Arsen Losenko
Author-email: arsenlosenko@protonmail.com
License: MIT
Keywords: transfer.sh command-line client tool utility cli CLI
Platform: UNKNOWN
Classifier: Development Status :: 3 - Alpha
Classifier: Intended Audience :: Developers
Classifier: Topic :: Utilities
Classifier: Environment :: Console
Classifier: License :: OSI Approved :: MIT License
Classifier: Programming Language :: Python :: 3.5
